moviespac/__init__.py
moviespac/film_client.py
moviespac/film_config.py
moviespac/schemas/__init__.py
moviespac/schemas/schemas.py
moviespac-0.0.1.dist-info/METADATA
moviespac-0.0.1.dist-info/WHEEL
moviespac-0.0.1.dist-info/top_level.txt
moviespac-0.0.1.dist-info/RECORD
